{
  "family": "my-demo-app-task",
  "networkMode": "awsvpc",
  "requiresCompatibilities": ["FARGATE"],
  "cpu": "256",
  "memory": "512",
  "executionRoleArn": "arn:aws:iam::615299772422:role/ecsTaskExecutionRole",
  "runtimePlatform": {
    "cpuArchitecture": "X86_64",
    "operatingSystemFamily": "LINUX"
  },
  "containerDefinitions": [
    {
      "name": "my-demo-app-container",
      "image": "PLACEHOLDER_IMAGE_WILL_BE_REPLACED_BY_PIPELINE",
      "cpu": 0,
      "essential": true,
      "portMappings": [
        {
          "containerPort": 3000,
          "protocol": "tcp"
        }
      ],
      "logConfiguration": {
        "logDriver": "awslogs",
        "options": {
          "awslogs-group": "/ecs/my-demo-app-task",
          "awslogs-create-group": "true",
          "awslogs-region": "eu-north-1",
          "awslogs-stream-prefix": "ecs"
        }
      }
    },
    {
      "name": "adot-collector",
      "image": "public.ecr.aws/aws-observability/aws-otel-collector:latest",
      "essential": false,
      "portMappings": [],
      "environment": [
        {
          "name": "AWS_PROMETHEUS_ENDPOINT",
          "value": "https://aps-workspaces.eu-north-1.amazonaws.com/workspaces/ws-0fb04e35-15b1-441f-9e1f-272a52c7e70a/api/v1/remote_write"
        }
      ],
      "logConfiguration": {
        "logDriver": "awslogs",
        "options": {
          "awslogs-group": "/ecs/my-demo-app-task",
          "awslogs-create-group": "true",
          "awslogs-region": "eu-north-1",
          "awslogs-stream-prefix": "adot"
        }
      }
    }
  ],
  "portMappins": [
    {
      "containerPort": 3000,
      "protocol": "tcp"
    },
    {
      "containerPort": 9100,
      "protocol": "tcp"
    }
  ],
  "essential": true
}
